{"_id":{"$oid":"564b7e57c0e086f9a4bb8076"},"logical_expression":{"operator":{"name":"\u003e="},"operand1":{"name":"AT004"},"operand2":{"name":"2"}},"name":"Own/lease 2+ vehicles - EXP 2+","expression_string":"(AT004 \u003e= 2)"}
{"_id":{"$oid":"564b7e57c0e086f9a4bb8077"},"logical_expression":{"operator":{"name":"REGEXP"},"operand1":{"name":"f036"},"operand2":{"name":"'[H]'"}},"name":"1+ Home"}
{"_id":{"$oid":"564b7e57c0e086f9a4bb8078"},"logical_expression":{"operand1":"f037","operand2":"'[A-F]'","operator":"REGEXP"},"name":"\u003c$100K"}
{"_id":{"$oid":"564b7e57c0e086f9a4bb8079"},"logical_expression":{"operand1":"f206","operand2":"'A01|A02|A03|A04|A05|A06|B07|B08|B09|B10|C11|C12|C13|C14|D15|D16|D17|D18|E19|E20|E21|F22|F23'","operator":"REGEXP"},"name":"Med-High Profitability"}
{"_id":{"$oid":"564b7e57c0e086f9a4bb807a"},"logical_expression":{"operand1":"f037","operand2":"'[G-L]'","operator":"REGEXP"},"name":"$100K+"}
{"_id":{"$oid":"564b7e57c0e086f9a4bb807b"},"logical_expression":{"operand1":"f037","operand2":"'[A-E]'","operator":"REGEXP"},"name":"\u003c$75K"}
{"_id":{"$oid":"564b7e57c0e086f9a4bb807c"},"logical_expression":{"operand1":"f037","operand2":"'[H-L]'","operator":"REGEXP"},"name":"$125K+"}
{"_id":{"$oid":"564b7e57c0e086f9a4bb807d"},"logical_expression":{"operand1":"f063","operand2":"'13|14|53|54'","operator":"REGEXP"},"name":"Person 1 College Graduate"}
{"_id":{"$oid":"564b7e57c0e086f9a4bb807e"},"logical_expression":{"operand1":"f063","operand2":"'11|12|15|51|52|55'","operator":"REGEXP"},"name":"Person 1 Not College Graduate"}
{"_id":{"$oid":"564b7e57c0e086f9a4bb807f"},"logical_expression":{"operand1":"f081","operand2":"'11|12|15|51|52|55'","operator":"REGEXP"},"name":"Person 2 Not College Graduate"}
{"_id":{"$oid":"564b7e57c0e086f9a4bb8080"},"logical_expression":{"operand1":"f081","operand2":"'13|14|53|54'","operator":"REGEXP"},"name":"Person 2 College Graduate"}
{"_id":{"$oid":"564b7e57c0e086f9a4bb8081"},"logical_expression":{"operand1":"f036","operand2":"'[R|T|U]'","operator":"REGEXP"},"name":"Does not own a home"}
{"_id":{"$oid":"564b7e57c0e086f9a4bb8082"},"logical_expression":{"operand1":{"operand1":{"operand1":{"operand1":"F061","operand2":"25","operator":"\u003e="},"operand2":{"operand1":"F079","operand2":"25","operator":"\u003e="},"operator":"OR"},"operand2":{"operand1":"F097","operand2":"25","operator":"\u003e="},"operator":"OR"},"operand2":{"operand1":{"operand1":"F115","operand2":"25","operator":"\u003e="},"operand2":{"operand1":{"operand1":"F133","operand2":"25","operator":"\u003e="},"operand2":{"operand1":"F151","operand2":"25","operator":"\u003e="},"operator":"OR"},"operator":"OR"},"operator":"OR"},"name":"Age 25+ HH"}
{"_id":{"$oid":"564b7e57c0e086f9a4bb8083"},"logical_expression":{"operand1":"vs_accord","operand2":"'1|2|3|4|5|6|7|8|9|10'","operator":"REGEXP"},"name":"Accord Intender"}
{"_id":{"$oid":"564b7e57c0e086f9a4bb8084"},"logical_expression":{"operand1":"vs_camry","operand2":"'1|2|3|4|5|6|7|8|9|10'","operator":"REGEXP"},"name":"Camry Intender"}
{"_id":{"$oid":"564b7e57c0e086f9a4bb8085"},"logical_expression":{"operand1":"vs_fusion","operand2":"'1|2|3|4|5|6|7|8|9|10'","operator":"REGEXP"},"name":"Fusion Intender"}
{"_id":{"$oid":"564b7e57c0e086f9a4bb8086"},"logical_expression":{"operand1":"vs_sonata","operand2":"'1|2|3|4|5|6|7|8|9|10'","operator":"REGEXP"},"name":"Sonsata Intender"}
{"_id":{"$oid":"564b7e57c0e086f9a4bb8087"},"logical_expression":{"operand1":"vs_altima","operand2":"'1|2|3|4|5|6|7|8|9|10'","operator":"REGEXP"},"name":"Altima Intender"}
{"_id":{"$oid":"564b7e57c0e086f9a4bb8088"},"logical_expression":{"operand1":"fwm_flag","operand2":"'1'","operator":"=="},"name":"FWM"}
{"_id":{"$oid":"564b7e57c0e086f9a4bb808a"},"logical_expression":{"operand1":"fandango_flag","operand2":"'1'","operator":"=="},"name":"Fandango"}
{"_id":{"$oid":"564b7e57c0e086f9a4bb808b"},"logical_expression":{"operand1":{"operand1":{"operand1":"f061","operand2":"25","operator":"\u003e="},"operand2":{"operand1":"f061","operand2":"49","operator":"\u003c="},"operator":"AND"},"operand2":{"operand1":{"operand1":{"operand1":"f079","operand2":"25","operator":"\u003e="},"operand2":{"operand1":"f079","operand2":"49","operator":"\u003c="},"operator":"AND"},"operand2":{"operand1":{"operand1":{"operand1":"f097","operand2":"25","operator":"\u003e="},"operand2":{"operand1":"f097","operand2":"49","operator":"\u003c="},"operator":"AND"},"operand2":{"operand1":{"operand1":{"operand1":"f115","operand2":"25","operator":"\u003e="},"operand2":{"operand1":"f115","operand2":"49","operator":"\u003c="},"operator":"AND"},"operand2":{"operand1":{"operand1":{"operand1":"f133","operand2":"25","operator":"\u003e="},"operand2":{"operand1":"f133","operand2":"49","operator":"\u003c="},"operator":"AND"},"operand2":{"operand1":{"operand1":"f151","operand2":"25","operator":"\u003e="},"operand2":{"operand1":"f151","operand2":"49","operator":"\u003c="},"operator":"AND"},"operator":"OR"},"operator":"OR"},"operator":"OR"},"operator":"OR"},"operator":"OR"},"name":"Age 25-49 HH"}
{"_id":{"$oid":"564b7e57c0e086f9a4bb808c"},"logical_expression":{"operand1":{"operand1":"vs_malibu","operand2":"'1|2|3|4|5|6|7|8|9|10'","operator":"REGEXP"},"operand2":{"operand1":{"operand1":"vs_fusion","operand2":"'1|2|3|4|5|6|7|8|9|10'","operator":"REGEXP"},"operand2":{"operand1":{"operand1":"vs_accord","operand2":"'1|2|3|4|5|6|7|8|9|10'","operator":"REGEXP"},"operand2":{"operand1":{"operand1":"vs_sonata","operand2":"'1|2|3|4|5|6|7|8|9|10'","operator":"REGEXP"},"operand2":{"operand1":{"operand1":"vs_altima","operand2":"'1|2|3|4|5|6|7|8|9|10'","operator":"REGEXP"},"operand2":{"operand1":"vs_camry","operand2":"'1|2|3|4|5|6|7|8|9|10'","operator":"REGEXP"},"operator":"OR"},"operator":"OR"},"operator":"OR"},"operator":"OR"},"operator":"OR"},"name":"Chevy"}
{"_id":{"$oid":"564b7e57c0e086f9a4bb808d"},"logical_expression":{"operand1":{"operand1":"vs_grandcherokee","operand2":"'1|2|3|4|5|6|7|8|9|10'","operator":"REGEXP"},"operand2":{"operand1":{"operand1":"vs_explorer","operand2":"'1|2|3|4|5|6|7|8|9|10'","operator":"REGEXP"},"operand2":{"operand1":{"operand1":"vs_highlander","operand2":"'1|2|3|4|5|6|7|8|9|10'","operator":"REGEXP"},"operand2":{"operand1":{"operand1":"vs_pilot","operand2":"'1|2|3|4|5|6|7|8|9|10'","operator":"REGEXP"},"operand2":{"operand1":{"operand1":"vs_4runner","operand2":"'1|2|3|4|5|6|7|8|9|10'","operator":"REGEXP"},"operand2":{"operand1":{"operand1":"vs_pathfinder","operand2":"'1|2|3|4|5|6|7|8|9|10'","operator":"REGEXP"},"operand2":{"operand1":{"operand1":"vs_mdx","operand2":"'1|2|3|4|5|6|7|8|9|10'","operator":"REGEXP"},"operand2":{"operand1":{"operand1":"vs_durango","operand2":"'1|2|3|4|5|6|7|8|9|10'","operator":"REGEXP"},"operand2":{"operand1":{"operand1":"vs_m_class","operand2":"'1|2|3|4|5|6|7|8|9|10'","operator":"REGEXP"},"operand2":{"operand1":{"operand1":"vs_x5","operand2":"'1|2|3|4|5|6|7|8|9|10'","operator":"REGEXP"},"operand2":{"operand1":"vs_santafe_sport","operand2":"'1|2|3|4|5|6|7|8|9|10'","operator":"REGEXP"},"operator":"OR"},"operator":"OR"},"operator":"OR"},"operator":"OR"},"operator":"OR"},"operator":"OR"},"operator":"OR"},"operator":"OR"},"operator":"OR"},"operator":"OR"},"name":"Chrysler"}
{"_id":{"$oid":"564cbc198fb35ad00404155d"},"logical_expression":{"operand1":"vs_jetta","operand2":"'1|2|3|4|5|6|7|8|9|10'","operator":"REGEXP"},"name":"Jetta Intender"}
{"_id":{"$oid":"565df8b9f6e4b72dd3765eb4"},"logical_expression":{"operator":{"name":"=="},"operand1":{"data_source":"Experian Gold","_id":"564f757fc3b5a004775f3cd7","description":"Zip Code","name":"F004"},"operand2":{"name":"'11501'"}},"name":"Test 1 Zip"}
